auto_smooth/__init__.py
auto_smooth/core.py
auto_smooth/metrics.py
auto_smooth/plotting.py
auto_smooth/utils.py
auto_smooth/filtering/__init__.py
auto_smooth/filtering/savgol.py
auto_smooth/smoothing/__init__.py
auto_smooth-0.1.0.dist-info/LICENSE
auto_smooth-0.1.0.dist-info/METADATA
auto_smooth-0.1.0.dist-info/WHEEL
auto_smooth-0.1.0.dist-info/top_level.txt
auto_smooth-0.1.0.dist-info/RECORD
