Metadata-Version: 2.1
Name: auto-smooth
Version: 0.1.0
Summary: Apply auto smoothing to a time series data.
Author-email: Kaymal <gutkyle@gmail.com>
License: MIT License
Project-URL: repository, https://github.com/kaymal/auto-smooth
Classifier: Operating System :: OS Independent
Classifier: Programming Language :: Python :: 3
Classifier: Programming Language :: Python :: 3.8
Classifier: Programming Language :: Python :: 3.9
Classifier: Programming Language :: Python :: 3.10
Classifier: Programming Language :: Python :: 3.11
Requires-Python: >=3.8
License-File: LICENSE
Requires-Dist: pandas
Requires-Dist: numpy
Requires-Dist: scipy
